WM/TK/__init__.py
WM/TK/elements.py
WM/Win32/__init__.py
WM/Win32/_core.py
WM/Win32/constants.py
WM/Win32/structures.py
WM/__init__.py
WM/core.py
WM/event.py
WM/images/0-00-000.png
WM/images/resize.ico
WM/main.py
WM/py.typed
WM/style.py
WM/views.py
574d-0.0.0rc0.dev2.dist-info/LICENSE
574d-0.0.0rc0.dev2.dist-info/WHEEL
574d-0.0.0rc0.dev2.dist-info/METADATA
574d-0.0.0rc0.dev2.dist-info/RECORD
