Metadata-Version: 2.1
Name: 574d
Version: 0.0.0rc0.dev2
Summary: A Window Manager for Tkinter On Windows 10
License: MIT
Keywords: TK,WM
Author: XxFULLDLCxX
Author-email: XxFULLDLCxX@gmail.com
Requires-Python: >=3.10,<4.0
Classifier: License :: OSI Approved :: MIT License
Classifier: Operating System :: Microsoft :: Windows
Classifier: Operating System :: Microsoft :: Windows :: Windows 10
Classifier: Programming Language :: Python :: 3
Classifier: Programming Language :: Python :: 3.10
Classifier: Programming Language :: Python :: 3.11
Project-URL: Bug Tracker, https://github.com/XxFULLDLCxX/WM/issues
Project-URL: Source, https://github.com/XxFULLDLCxX/WM
